setup.py
dm/__init__.py
dm.zope.mockup.egg-info/PKG-INFO
dm.zope.mockup.egg-info/SOURCES.txt
dm.zope.mockup.egg-info/dependency_links.txt
dm.zope.mockup.egg-info/namespace_packages.txt
dm.zope.mockup.egg-info/not-zip-safe
dm.zope.mockup.egg-info/top_level.txt
dm/zope/__init__.py
dm/zope/mockup/LICENSE.txt
dm/zope/mockup/README.txt
dm/zope/mockup/VERSION.txt
dm/zope/mockup/__init__.py
dm/zope/mockup/tests.py
dm/zope/mockup/zodb.py