Metadata-Version: 1.1
Name: dm.zope.mockup
Version: 0.1.1p1
Summary: A (still small) repository of mockup objects for Zope [2] tests.
Home-page: http://pypi.python.org/pypi/dm.zope.mockup
Author: Dieter Maurer
Author-email: dieter@handshake.de
License: BSD
Keywords: test mockup
Platform: UNKNOWN
Classifier: Development Status :: 5 - Production/Stable
Classifier: Intended Audience :: Developers
Classifier: License :: OSI Approved :: BSD License
Classifier: Framework :: Zope2
Classifier: Operating System :: OS Independent
Classifier: Programming Language :: Python
Classifier: Topic :: Utilities
